wesign_sdk/__about__.py
wesign_sdk/__init__.py
wesign_sdk/models.py
wesign_sdk/recipient_meta_info.py
wesign_sdk/sdk.py
wesign_sdk/test_sdk.py
wesign_sdk/custom_exceptions/__init__.py
wesign_sdk/custom_exceptions/custom_exceptions.py
wesign_sdk-0.0.10.dist-info/METADATA
wesign_sdk-0.0.10.dist-info/WHEEL
wesign_sdk-0.0.10.dist-info/licenses/LICENSE.txt
wesign_sdk-0.0.10.dist-info/RECORD
