Metadata-Version: 2.4
Name: wesign-sdk
Version: 0.0.10
Summary: Python SDK for Wesign HTTP API
Project-URL: Documentation, https://github.com/santoshpanigrahy/wesign_sdk?tab=readme-ov-file#wesign-sdk
Project-URL: Issues, https://github.com/santoshpanigrahy/wesign_sdk/issues
Project-URL: Source, https://github.com/santoshpanigrahy/wesign_sdk
Author-email: Mayur Patil <mayur.patil1211@gmail.com>
License-Expression: MIT
License-File: LICENSE.txt
Classifier: Development Status :: 4 - Beta
Classifier: Programming Language :: Python
Classifier: Programming Language :: Python :: 3.8
Classifier: Programming Language :: Python :: 3.9
Classifier: Programming Language :: Python :: 3.10
Classifier: Programming Language :: Python :: 3.11
Classifier: Programming Language :: Python :: 3.12
Classifier: Programming Language :: Python :: Implementation :: CPython
Classifier: Programming Language :: Python :: Implementation :: PyPy
Requires-Python: >=3.8
Requires-Dist: pydantic
Requires-Dist: requests
Requires-Dist: responses
